<?xml version="1.0"?>
<!DOCTYPE softwarelist SYSTEM "softwarelist.dtd">
<!--
This file was generated directly from a TOSEC data file as available freely on tosecdev.org.
Credit goes to the TOSECDEV team for building this vast database over the years.
-->
<softwarelist name="amiga_tosec_pd_cactus" description="Amiga TOSEC - Cactus">

	<software name="cactus01" supported="no">
		<description>Cactus #01 - Diverses (de)</description>
		<year>1988</year>
		<publisher>Commodore Amiga Creativ Und Software Usergruppe</publisher>

		<part name="flop1" interface="floppy_3_5">
			<dataarea name="rom" size="901120">
				<rom name="cactus #01 - diverses (1988)(commodore amiga creativ und software usergruppe)(de).adf" size="901120" crc="7d150873" sha1="f7547cd84d2a56db4162e839fe4f0e933fbe07f8"/>
			</dataarea>
		</part>
	</software>

	<software name="cactus02" supported="no">
		<description>Cactus #02 - DFU-Programme (de, 1988-07)</description>
		<year>1988</year>
		<publisher>Commodore Amiga Creativ Und Software Usergruppe</publisher>

		<part name="flop1" interface="floppy_3_5">
			<dataarea name="rom" size="901120">
				<rom name="cactus #02 - dfu-programme (1988-07)(commodore amiga creativ und software usergruppe)(de).adf" size="901120" crc="951f5db7" sha1="d42b6fe1a82a94d8002b2b3c330457c97b7c0f8b"/>
			</dataarea>
		</part>
	</software>

	<software name="cactus03" supported="no">
		<description>Cactus #03 - Digi-Sounds I (de)</description>
		<year>1988</year>
		<publisher>Commodore Amiga Creativ Und Software Usergruppe</publisher>

		<part name="flop1" interface="floppy_3_5">
			<feature name="part_id" value="Bad corrupt file"/>
			<dataarea name="rom" size="901120">
				<rom name="cactus #03 - digi-sounds i (1988)(commodore amiga creativ und software usergruppe)(de)[b corrupt file].adf" size="901120" crc="1ee7714a" sha1="dca66d038677ce56f209e20d4214793153dd4d1c" status="baddump"/>
			</dataarea>
		</part>
	</software>

	<software name="cactus04" supported="no">
		<description>Cactus #04 - Diashow I (de)</description>
		<year>1988</year>
		<publisher>Commodore Amiga Creativ Und Software Usergruppe</publisher>

		<part name="flop1" interface="floppy_3_5">
			<dataarea name="rom" size="901120">
				<rom name="cactus #04 - diashow i (1988)(commodore amiga creativ und software usergruppe)(de).adf" size="901120" crc="c8539c76" sha1="90db69f92fe043f54fae337a83de1755211d78fb"/>
			</dataarea>
		</part>
	</software>

	<software name="cactus05" supported="no">
		<description>Cactus #05 - Utilities (de)</description>
		<year>1988</year>
		<publisher>Commodore Amiga Creativ Und Software Usergruppe</publisher>

		<part name="flop1" interface="floppy_3_5">
			<dataarea name="rom" size="901120">
				<rom name="cactus #05 - utilities (1988)(commodore amiga creativ und software usergruppe)(de).adf" size="901120" crc="9dea5895" sha1="46c9e345c6c3df49bf0005b38c57d485b4355001"/>
			</dataarea>
		</part>
	</software>

	<software name="cactus06" supported="no">
		<description>Cactus #06 - Grafikdemos (de)</description>
		<year>1988</year>
		<publisher>Commodore Amiga Creativ Und Software Usergruppe</publisher>

		<part name="flop1" interface="floppy_3_5">
			<dataarea name="rom" size="901120">
				<rom name="cactus #06 - grafikdemos (1988)(commodore amiga creativ und software usergruppe)(de).adf" size="901120" crc="65338850" sha1="bfe285d9da1720d66d626388291cf1b4bd828f8f"/>
			</dataarea>
		</part>
	</software>

	<software name="cactus07" supported="no">
		<description>Cactus #07 - TextEditor-Programme (de)</description>
		<year>1988</year>
		<publisher>Commodore Amiga Creativ Und Software Usergruppe</publisher>

		<part name="flop1" interface="floppy_3_5">
			<dataarea name="rom" size="901120">
				<rom name="cactus #07 - texteditor-programme (1988)(commodore amiga creativ und software usergruppe)(de).adf" size="901120" crc="ee011b20" sha1="6f30bba8bdf389452bbd53d9643c32a44b950fa5"/>
			</dataarea>
		</part>
	</software>

	<software name="cactus08" supported="no">
		<description>Cactus #08 - Digi-Sounds II (de)</description>
		<year>1988</year>
		<publisher>Commodore Amiga Creativ Und Software Usergruppe</publisher>

		<part name="flop1" interface="floppy_3_5">
			<dataarea name="rom" size="901120">
				<rom name="cactus #08 - digi-sounds ii (1988)(commodore amiga creativ und software usergruppe)(de).adf" size="901120" crc="9f3dc94d" sha1="0429741456b3b990bca6eb7a196e64756b9420c8"/>
			</dataarea>
		</part>
	</software>

	<software name="cactus09" supported="no">
		<description>Cactus #09 - Textsystem Komplett (de, 1988-08)</description>
		<year>1988</year>
		<publisher>Commodore Amiga Creativ Und Software Usergruppe</publisher>

		<part name="flop1" interface="floppy_3_5">
			<dataarea name="rom" size="901120">
				<rom name="cactus #09 - textsystem komplett (1988-08)(commodore amiga creativ und software usergruppe)(de).adf" size="901120" crc="b05ae8ad" sha1="0241256a3b06b26fc495886e0ae32ce3c8841826"/>
			</dataarea>
		</part>
	</software>

	<software name="cactus10" supported="no">
		<description>Cactus #10 - Directory-Utilities (de, 1988-08)</description>
		<year>1988</year>
		<publisher>Commodore Amiga Creativ Und Software Usergruppe</publisher>

		<part name="flop1" interface="floppy_3_5">
			<dataarea name="rom" size="901120">
				<rom name="cactus #10 - directory-utilities (1988-08)(commodore amiga creativ und software usergruppe)(de).adf" size="901120" crc="df0267c1" sha1="4896f1741cf13c84c48c575957d9e8051d1c2e06"/>
			</dataarea>
		</part>
	</software>

	<software name="cactus11" supported="no">
		<description>Cactus #11 - Monitor-Programme (de, 1988-09)</description>
		<year>1988</year>
		<publisher>Commodore Amiga Creativ Und Software Usergruppe</publisher>

		<part name="flop1" interface="floppy_3_5">
			<dataarea name="rom" size="901120">
				<rom name="cactus #11 - monitor-programme (1988-09)(commodore amiga creativ und software usergruppe)(de).adf" size="901120" crc="39f7c31f" sha1="1c49dac09258ae8445cc78c349ffe77e659ff85a"/>
			</dataarea>
		</part>
	</software>

	<software name="cactus12" supported="no">
		<description>Cactus #12 - Drucker-Utilities (de, 1988-10)</description>
		<year>1988</year>
		<publisher>Commodore Amiga Creativ Und Software Usergruppe</publisher>

		<part name="flop1" interface="floppy_3_5">
			<dataarea name="rom" size="901120">
				<rom name="cactus #12 - drucker-utilities (1988-10)(commodore amiga creativ und software usergruppe)(de).adf" size="901120" crc="eb12ca26" sha1="907cab37f76f34dc2e4fc2ba3d8a6fdea8ca0c33"/>
			</dataarea>
		</part>
	</software>

	<software name="cactus13" supported="no">
		<description>Cactus #13 - Cats (de, 1988-10)</description>
		<year>1988</year>
		<publisher>Commodore Amiga Creativ Und Software Usergruppe</publisher>

		<part name="flop1" interface="floppy_3_5">
			<dataarea name="rom" size="901120">
				<rom name="cactus #13 - cats (1988-10)(commodore amiga creativ und software usergruppe)(de).adf" size="901120" crc="018d3c1a" sha1="b0bd955dd2ef2e068d9779cf79280b6933e25f11"/>
			</dataarea>
		</part>
		<part name="flop2" interface="floppy_3_5">
			<feature name="part_id" value="Alt bootro removed"/>
			<dataarea name="rom" size="901120">
				<rom name="cactus #13 - cats (1988-10)(commodore amiga creativ und software usergruppe)(de)[a bootro removed].adf" size="901120" crc="302fc464" sha1="b8ac35169ccc3473cb517a01e49af648827f8493"/>
			</dataarea>
		</part>
	</software>

	<software name="cactus14" supported="no">
		<description>Cactus #14 - Mandelbrot-Fractale (de, 1988-10)</description>
		<year>1988</year>
		<publisher>Commodore Amiga Creativ Und Software Usergruppe</publisher>

		<part name="flop1" interface="floppy_3_5">
			<dataarea name="rom" size="901120">
				<rom name="cactus #14 - mandelbrot-fractale (1988-10)(commodore amiga creativ und software usergruppe)(de).adf" size="901120" crc="8e3e56fe" sha1="47f1f3438c6ba55140e52d4f839581a9d3ef775e"/>
			</dataarea>
		</part>
	</software>

	<software name="cactus15" supported="no">
		<description>Cactus #15 - Spiele (de, 1988-10)</description>
		<year>1988</year>
		<publisher>Commodore Amiga Creativ Und Software Usergruppe</publisher>

		<part name="flop1" interface="floppy_3_5">
			<dataarea name="rom" size="901120">
				<rom name="cactus #15 - spiele (1988-10)(commodore amiga creativ und software usergruppe)(de).adf" size="901120" crc="4c90ff6b" sha1="35608dba85edc99dbb7945608cbed22da4fc328e"/>
			</dataarea>
		</part>
	</software>

	<software name="cactus16" supported="no">
		<description>Cactus #16 - Sounds (de, 1988-11)</description>
		<year>1988</year>
		<publisher>Commodore Amiga Creativ Und Software Usergruppe</publisher>

		<part name="flop1" interface="floppy_3_5">
			<dataarea name="rom" size="901120">
				<rom name="cactus #16 - sounds (1988-11)(commodore amiga creativ und software usergruppe)(de).adf" size="901120" crc="e11e6502" sha1="3cb028703fe6e796db7e4396d3ff4c76571b77e4"/>
			</dataarea>
		</part>
	</software>

	<software name="cactus17" supported="no">
		<description>Cactus #17 - Diashow III (de, 1988-11)</description>
		<year>1988</year>
		<publisher>Commodore Amiga Creativ Und Software Usergruppe</publisher>

		<part name="flop1" interface="floppy_3_5">
			<dataarea name="rom" size="901120">
				<rom name="cactus #17 - diashow iii (1988-11)(commodore amiga creativ und software usergruppe)(de).adf" size="901120" crc="24bc6187" sha1="8ec5bc387dc167f2f79425ffd48177302418f9cb"/>
			</dataarea>
		</part>
		<part name="flop2" interface="floppy_3_5">
			<feature name="part_id" value="Alt bootro removed"/>
			<dataarea name="rom" size="901120">
				<rom name="cactus #17 - diashow iii (1988-11)(commodore amiga creativ und software usergruppe)(de)[a bootro removed].adf" size="901120" crc="5c56eca9" sha1="301aff192affb1839226b0ba131227455c925500"/>
			</dataarea>
		</part>
	</software>

	<software name="cactus18" supported="no">
		<description>Cactus #18 - Viren-Killer (de, 1988-11)</description>
		<year>1988</year>
		<publisher>Commodore Amiga Creativ Und Software Usergruppe</publisher>

		<part name="flop1" interface="floppy_3_5">
			<dataarea name="rom" size="901120">
				<rom name="cactus #18 - viren-killer (1988-11)(commodore amiga creativ und software usergruppe)(de).adf" size="901120" crc="1ca622a1" sha1="636d54fe8e62c8152fe1750bd02cdeb1e4165a7c"/>
			</dataarea>
		</part>
	</software>

	<software name="cactus19" supported="no">
		<description>Cactus #19 - Kopier-Programme (de, 1988-11)</description>
		<year>1988</year>
		<publisher>Commodore Amiga Creativ Und Software Usergruppe</publisher>

		<part name="flop1" interface="floppy_3_5">
			<dataarea name="rom" size="901120">
				<rom name="cactus #19 - kopier-programme (1988-11)(commodore amiga creativ und software usergruppe)(de).adf" size="901120" crc="04f68dd6" sha1="002aa9bde5244f628095191788267d07463dedce"/>
			</dataarea>
		</part>
	</software>

	<software name="cactus20" supported="no">
		<description>Cactus #20 - Animationen I (de, 1988-11)</description>
		<year>1988</year>
		<publisher>Commodore Amiga Creativ Und Software Usergruppe</publisher>

		<part name="flop1" interface="floppy_3_5">
			<dataarea name="rom" size="901120">
				<rom name="cactus #20 - animationen i (1988-11)(commodore amiga creativ und software usergruppe)(de).adf" size="901120" crc="56167949" sha1="6b361bc712ebfa16b9e58ee6bcd638d54886625a"/>
			</dataarea>
		</part>
	</software>

	<software name="cactus21" supported="no">
		<description>Cactus #21 - Animationen II (de, 1988-11)</description>
		<year>1988</year>
		<publisher>Commodore Amiga Creativ Und Software Usergruppe</publisher>

		<part name="flop1" interface="floppy_3_5">
			<dataarea name="rom" size="901120">
				<rom name="cactus #21 - animationen ii (1988-11)(commodore amiga creativ und software usergruppe)(de).adf" size="901120" crc="f253a178" sha1="957815e58b4a4e767c4d457dc8b2cbae44f64c67"/>
			</dataarea>
		</part>
	</software>

	<software name="cactus22" supported="no">
		<description>Cactus #22 - Risk (de, v3.0, 1988-12)</description>
		<year>1988</year>
		<publisher>Commodore Amiga Creativ Und Software Usergruppe</publisher>

		<part name="flop1" interface="floppy_3_5">
			<dataarea name="rom" size="901120">
				<rom name="cactus #22 - risk v3.0 (1988-12)(commodore amiga creativ und software usergruppe)(de).adf" size="901120" crc="245a74e2" sha1="c6f084128bf879fc82eadde1d06d7048fee284e0"/>
			</dataarea>
		</part>
	</software>

	<software name="cactus23" supported="no">
		<description>Cactus #23 - Haushaltsbuch (de, 1988-12)</description>
		<year>1988</year>
		<publisher>Commodore Amiga Creativ Und Software Usergruppe</publisher>

		<part name="flop1" interface="floppy_3_5">
			<dataarea name="rom" size="901120">
				<rom name="cactus #23 - haushaltsbuch (1988-12)(commodore amiga creativ und software usergruppe)(de).adf" size="901120" crc="7e1e744f" sha1="1c57ff838fa5868e5065a8ed983fa81b9f585e7a"/>
			</dataarea>
		</part>
	</software>

	<software name="cactus24" supported="no">
		<description>Cactus #24 - Ausgeflipptes (de, 1989-01)</description>
		<year>1989</year>
		<publisher>Commodore Amiga Creativ Und Software Usergruppe</publisher>

		<part name="flop1" interface="floppy_3_5">
			<dataarea name="rom" size="901120">
				<rom name="cactus #24 - ausgeflipptes (1989-01)(commodore amiga creativ und software usergruppe)(de).adf" size="901120" crc="fe82e371" sha1="df1a9495ea871a34afc7d7ad4c1a32174c9141ad"/>
			</dataarea>
		</part>
	</software>

	<software name="cactus25" supported="no">
		<description>Cactus #25 - Alles fur den Texter (de, 1989-02)</description>
		<year>1989</year>
		<publisher>Commodore Amiga Creativ Und Software Usergruppe</publisher>

		<part name="flop1" interface="floppy_3_5">
			<dataarea name="rom" size="901120">
				<rom name="cactus #25 - alles fur den texter (1989-02)(commodore amiga creativ und software usergruppe)(de).adf" size="901120" crc="0614267d" sha1="a7a7fa68265a80f30cdadc47b4579a7457746530"/>
			</dataarea>
		</part>
	</software>

	<software name="cactus26" supported="no">
		<description>Cactus #26 - Sounds II (de, 1989-03)</description>
		<year>1989</year>
		<publisher>Commodore Amiga Creativ Und Software Usergruppe</publisher>

		<part name="flop1" interface="floppy_3_5">
			<dataarea name="rom" size="901120">
				<rom name="cactus #26 - sounds ii (1989-03)(commodore amiga creativ und software usergruppe)(de).adf" size="901120" crc="8129937d" sha1="3263482f4575172839bb496a98ff6b6b6465acb2"/>
			</dataarea>
		</part>
	</software>

	<software name="cactus27" supported="no">
		<description>Cactus #27 - Icons (de, 1989-04)</description>
		<year>1989</year>
		<publisher>Commodore Amiga Creativ Und Software Usergruppe</publisher>

		<part name="flop1" interface="floppy_3_5">
			<dataarea name="rom" size="901120">
				<rom name="cactus #27 - icons (1989-04)(commodore amiga creativ und software usergruppe)(de).adf" size="901120" crc="85f87338" sha1="b4f25c106b48897f487b8fd18db27b886e3efb35"/>
			</dataarea>
		</part>
	</software>

	<software name="cactus28" supported="no">
		<description>Cactus #28 - Utilities III (de, 1989-05)</description>
		<year>1989</year>
		<publisher>Commodore Amiga Creativ Und Software Usergruppe</publisher>

		<part name="flop1" interface="floppy_3_5">
			<dataarea name="rom" size="901120">
				<rom name="cactus #28 - utilities iii (1989-05)(commodore amiga creativ und software usergruppe)(de).adf" size="901120" crc="d988325a" sha1="43d9afdd5ae742293bcbe34125e96ff44fae57e7"/>
			</dataarea>
		</part>
	</software>

	<software name="cactus29" supported="no">
		<description>Cactus #29 - Spiele II (de, 1989-06)</description>
		<year>1989</year>
		<publisher>Commodore Amiga Creativ Und Software Usergruppe</publisher>

		<part name="flop1" interface="floppy_3_5">
			<dataarea name="rom" size="901120">
				<rom name="cactus #29 - spiele ii (1989-06)(commodore amiga creativ und software usergruppe)(de).adf" size="901120" crc="6b00c4e1" sha1="8f43b7c4663e23e79a4599cc32e7b1ad4576d22a"/>
			</dataarea>
		</part>
	</software>

	<software name="cactus30" supported="no">
		<description>Cactus #30 - Superliga 88-89 (de)</description>
		<year>1989</year>
		<publisher>Commodore Amiga Creativ Und Software Usergruppe</publisher>

		<part name="flop1" interface="floppy_3_5">
			<dataarea name="rom" size="901120">
				<rom name="cactus #30 - superliga 88-89 (1989)(commodore amiga creativ und software usergruppe)(de).adf" size="901120" crc="32e44291" sha1="722123352fbdd32ceb3356f26582a87cb978f19d"/>
			</dataarea>
		</part>
	</software>

	<software name="cactus31" supported="no">
		<description>Cactus #31 - Anwendungen (de, 1989-07)</description>
		<year>1989</year>
		<publisher>Commodore Amiga Creativ Und Software Usergruppe</publisher>

		<part name="flop1" interface="floppy_3_5">
			<dataarea name="rom" size="901120">
				<rom name="cactus #31 - anwendungen (1989-07)(commodore amiga creativ und software usergruppe)(de).adf" size="901120" crc="ad271dab" sha1="27e16b798cae1b3ab5f9e6311959fe83fdb3f693"/>
			</dataarea>
		</part>
	</software>

	<software name="cactus32" supported="no">
		<description>Cactus #32 - Spiele III (de, 1989-07)</description>
		<year>1989</year>
		<publisher>Commodore Amiga Creativ Und Software Usergruppe</publisher>

		<part name="flop1" interface="floppy_3_5">
			<dataarea name="rom" size="901120">
				<rom name="cactus #32 - spiele iii (1989-07)(commodore amiga creativ und software usergruppe)(de).adf" size="901120" crc="e9254469" sha1="69f64e6339046e8bfcdf6fb675a2b32210dcef3e"/>
			</dataarea>
		</part>
	</software>

	<software name="cactus33" supported="no">
		<description>Cactus #33 - GFA-Basic (de, 1989-09)</description>
		<year>1989</year>
		<publisher>Commodore Amiga Creativ Und Software Usergruppe</publisher>

		<part name="flop1" interface="floppy_3_5">
			<dataarea name="rom" size="901120">
				<rom name="cactus #33 - gfa-basic (1989-09)(commodore amiga creativ und software usergruppe)(de).adf" size="901120" crc="b961d06c" sha1="905f6d355ebdb81d30c492d7929504de9738f992"/>
			</dataarea>
		</part>
	</software>

	<software name="cactus34" supported="no">
		<description>Cactus #34 - Grafik und Soundwerkzeuge (de, 1989-09)</description>
		<year>1989</year>
		<publisher>Commodore Amiga Creativ Und Software Usergruppe</publisher>

		<part name="flop1" interface="floppy_3_5">
			<dataarea name="rom" size="901120">
				<rom name="cactus #34 - grafik und soundwerkzeuge (1989-09)(commodore amiga creativ und software usergruppe)(de).adf" size="901120" crc="c7cd407d" sha1="ed27a5145f9b5ef74f185869f796c46bab1f8db9"/>
			</dataarea>
		</part>
	</software>

	<software name="cactus35" supported="no">
		<description>Cactus #35 - Animationen III (de, 1989-10)</description>
		<year>1989</year>
		<publisher>Commodore Amiga Creativ Und Software Usergruppe</publisher>

		<part name="flop1" interface="floppy_3_5">
			<dataarea name="rom" size="901120">
				<rom name="cactus #35 - animationen iii (1989-10)(commodore amiga creativ und software usergruppe)(de).adf" size="901120" crc="e5b92571" sha1="001156c711de47d4db2718d04368e047ceedf2f8"/>
			</dataarea>
		</part>
	</software>

	<software name="cactus36" supported="no">
		<description>Cactus #36 - Diskanwender (de, 1990-04)</description>
		<year>1990</year>
		<publisher>Commodore Amiga Creativ Und Software Usergruppe</publisher>

		<part name="flop1" interface="floppy_3_5">
			<dataarea name="rom" size="901120">
				<rom name="cactus #36 - diskanwender (1990-04)(commodore amiga creativ und software usergruppe)(de).adf" size="901120" crc="32b9d718" sha1="af5058360a41ad72095e9b796ca392479d041bf2"/>
			</dataarea>
		</part>
	</software>

	<software name="cactus37" supported="no">
		<description>Cactus #37 - Sonix-Musikstucke I (de, 1990-04)</description>
		<year>1990</year>
		<publisher>Commodore Amiga Creativ Und Software Usergruppe</publisher>

		<part name="flop1" interface="floppy_3_5">
			<dataarea name="rom" size="901120">
				<rom name="cactus #37 - sonix-musikstucke i (1990-04)(commodore amiga creativ und software usergruppe)(de).adf" size="901120" crc="0b6bef17" sha1="8d1c2a9e11b3a07af09679eb5ea1c77fe2a13411"/>
			</dataarea>
		</part>
	</software>

	<software name="cactus38" supported="no">
		<description>Cactus #38 - Sonix-Musikstucke II (de, 1990-04)</description>
		<year>1990</year>
		<publisher>Commodore Amiga Creativ Und Software Usergruppe</publisher>

		<part name="flop1" interface="floppy_3_5">
			<dataarea name="rom" size="901120">
				<rom name="cactus #38 - sonix-musikstucke ii (1990-04)(commodore amiga creativ und software usergruppe)(de).adf" size="901120" crc="9c08b10f" sha1="53e2bc0911d2a69199ede88b7beb365d125a9ff9"/>
			</dataarea>
		</part>
	</software>

	<software name="cactus39" supported="no">
		<description>Cactus #39 - Diskanwender und Utilities (de, 1990-09)</description>
		<year>1990</year>
		<publisher>Commodore Amiga Creativ Und Software Usergruppe</publisher>

		<part name="flop1" interface="floppy_3_5">
			<dataarea name="rom" size="901120">
				<rom name="cactus #39 - diskanwender und utilities (1990-09)(commodore amiga creativ und software usergruppe)(de).adf" size="901120" crc="24707745" sha1="9a927e632e6b464268c014269abd6a74bc966914"/>
			</dataarea>
		</part>
	</software>

	<software name="cactus40" supported="no">
		<description>Cactus #40 - Label-Paint (de, 1990-11)</description>
		<year>1990</year>
		<publisher>Commodore Amiga Creativ Und Software Usergruppe</publisher>

		<part name="flop1" interface="floppy_3_5">
			<dataarea name="rom" size="901120">
				<rom name="cactus #40 - label-paint (1990-11)(commodore amiga creativ und software usergruppe)(de).adf" size="901120" crc="aa65fa24" sha1="01d5018ba97e359b5626abdfe689eb959cab7ebd"/>
			</dataarea>
		</part>
	</software>

	<software name="cactus41" supported="no">
		<description>Cactus #41 - Spiele (de, 1990-11)</description>
		<year>1990</year>
		<publisher>Commodore Amiga Creativ Und Software Usergruppe</publisher>

		<part name="flop1" interface="floppy_3_5">
			<dataarea name="rom" size="901120">
				<rom name="cactus #41 - spiele (1990-11)(commodore amiga creativ und software usergruppe)(de).adf" size="901120" crc="ec5cbdca" sha1="35e7dad787ca0a828f20065f9f84b355d2d18d1c"/>
			</dataarea>
		</part>
	</software>

	<software name="cactus42" supported="no">
		<description>Cactus #42 - Updates und Utilties (de, 1991-01)</description>
		<year>1991</year>
		<publisher>Commodore Amiga Creativ Und Software Usergruppe</publisher>

		<part name="flop1" interface="floppy_3_5">
			<dataarea name="rom" size="901120">
				<rom name="cactus #42 - updates und utilties (1991-01)(commodore amiga creativ und software usergruppe)(de).adf" size="901120" crc="f55a6fce" sha1="44026b3874a5532be40187691a49c6c23023f3c2"/>
			</dataarea>
		</part>
	</software>

	<software name="cactus43" supported="no">
		<description>Cactus #43 - Utilities (de, 1991-06)</description>
		<year>1991</year>
		<publisher>Commodore Amiga Creativ Und Software Usergruppe</publisher>

		<part name="flop1" interface="floppy_3_5">
			<dataarea name="rom" size="901120">
				<rom name="cactus #43 - utilities (1991-06)(commodore amiga creativ und software usergruppe)(de).adf" size="901120" crc="0b4cdcb8" sha1="0d714fc81d76a1e7735338a7ce55296e9ecae302"/>
			</dataarea>
		</part>
	</software>

	<software name="cactus44" supported="no">
		<description>Cactus #44 - Spiele (de, 1991-10)</description>
		<year>1991</year>
		<publisher>Commodore Amiga Creativ Und Software Usergruppe</publisher>

		<part name="flop1" interface="floppy_3_5">
			<dataarea name="rom" size="901120">
				<rom name="cactus #44 - spiele (1991-10)(commodore amiga creativ und software usergruppe)(de).adf" size="901120" crc="978495ab" sha1="463eb16a55d9dd6438a66a0bdeea3d3c4a2b5514"/>
			</dataarea>
		</part>
	</software>

	<software name="cactus45" supported="no">
		<description>Cactus #45 - Ordnung und Verwaltung (de, 1992-02)</description>
		<year>1992</year>
		<publisher>Commodore Amiga Creativ Und Software Usergruppe</publisher>

		<part name="flop1" interface="floppy_3_5">
			<dataarea name="rom" size="901120">
				<rom name="cactus #45 - ordnung und verwaltung (1992-02)(commodore amiga creativ und software usergruppe)(de).adf" size="901120" crc="1927478e" sha1="d70efb7025dbd3daea531458d6d0de8bf4af6387"/>
			</dataarea>
		</part>
	</software>

	<software name="cactus46" supported="no">
		<description>Cactus #46 - Spiele (de, 1992-02)</description>
		<year>1992</year>
		<publisher>Commodore Amiga Creativ Und Software Usergruppe</publisher>

		<part name="flop1" interface="floppy_3_5">
			<dataarea name="rom" size="901120">
				<rom name="cactus #46 - spiele (1992-02)(commodore amiga creativ und software usergruppe)(de).adf" size="901120" crc="43d169d6" sha1="fea46a2eac23afe95ac1091e82311cc033777490"/>
			</dataarea>
		</part>
	</software>

	<software name="cactus47" supported="no">
		<description>Cactus #47 - DFU (de, 1992-04)</description>
		<year>1992</year>
		<publisher>Commodore Amiga Creativ Und Software Usergruppe</publisher>

		<part name="flop1" interface="floppy_3_5">
			<dataarea name="rom" size="901120">
				<rom name="cactus #47 - dfu (1992-04)(commodore amiga creativ und software usergruppe)(de).adf" size="901120" crc="8782f352" sha1="f1a25cb3a614a0b663a1002930745867ee84c27b"/>
			</dataarea>
		</part>
	</software>

	<software name="cactus48" supported="no">
		<description>Cactus #48 - Spiele (de, 1992-05)</description>
		<year>1992</year>
		<publisher>Commodore Amiga Creativ Und Software Usergruppe</publisher>

		<part name="flop1" interface="floppy_3_5">
			<dataarea name="rom" size="901120">
				<rom name="cactus #48 - spiele (1992-05)(commodore amiga creativ und software usergruppe)(de).adf" size="901120" crc="d33c5d43" sha1="5721c0e6d3f2f58e45265940a6e71efd73e5e523"/>
			</dataarea>
		</part>
	</software>

	<software name="cactus49" supported="no">
		<description>Cactus #49 - Anwender und Dateien (de, 1992-08)</description>
		<year>1992</year>
		<publisher>Commodore Amiga Creativ Und Software Usergruppe</publisher>

		<part name="flop1" interface="floppy_3_5">
			<dataarea name="rom" size="901120">
				<rom name="cactus #49 - anwender und dateien (1992-08)(commodore amiga creativ und software usergruppe)(de).adf" size="901120" crc="2309971b" sha1="d978df98d27f1e9ae55712b64c0ad94e58d01e79"/>
			</dataarea>
		</part>
	</software>

</softwarelist>
